gradio_path_selector/__init__.py
gradio_path_selector/path_selector.py
gradio_path_selector/path_selector.pyi
gradio_path_selector/templates/component/index.js
gradio_path_selector/templates/component/style.css
gradio_path_selector/templates/example/index.js
gradio_path_selector/templates/example/style.css
gradio_path_selector-0.1.3.dist-info/METADATA
gradio_path_selector-0.1.3.dist-info/WHEEL
gradio_path_selector-0.1.3.dist-info/RECORD
