Metadata-Version: 2.3
Name: gradio_path_selector
Version: 0.1.3
Summary: A path Selector component for Gradio
Project-URL: repository, https://github.com/ncassereau-idris/gradio_path_selector
Author-email: Nathan Cassereau <nathan.cassereau@gmail.com>
License-Expression: MIT
Keywords: gradio-custom-component,gradio-template-Fallback
Classifier: Development Status :: 3 - Alpha
Classifier: Operating System :: OS Independent
Classifier: Programming Language :: Python :: 3
Classifier: Programming Language :: Python :: 3 :: Only
Classifier: Programming Language :: Python :: 3.8
Classifier: Programming Language :: Python :: 3.9
Classifier: Programming Language :: Python :: 3.10
Classifier: Programming Language :: Python :: 3.11
Classifier: Topic :: Scientific/Engineering
Classifier: Topic :: Scientific/Engineering :: Artificial Intelligence
Classifier: Topic :: Scientific/Engineering :: Visualization
Requires-Python: >=3.8
Requires-Dist: gradio<5.0,>=4.0
Provides-Extra: dev
Requires-Dist: build; extra == 'dev'
Requires-Dist: twine; extra == 'dev'
